[{
"id":0,"img":"http://image8.wbiao.co/mall/4b487eb057524149981c2877ed175a70.jpg?x-oss-process=image/resize,w_260,h_260","name":"天俊TISSOT","pinpai":"力洛克系列"},
{"id":1,"img":"http://image8.wbiao.co/mall/45da8074454642978946dcfe8f91f0dc.jpg?x-oss-process=image/resize,w_260,h_260","name":"美度MIDO","pinpai":"贝伦赛丽系列"
},{"id":2,"img":"http://image8.wbiao.co/mall/cc220afe5a6a4a9f9f0abe2ee1279472.jpg?x-oss-process=image/resize,w_260,h_260","name":"赫柏林Michel Herbelin","pinpai":"都市系列"},{
"id":3,"img":"http://image8.wbiao.co/mall/efb48b665c6540dd914314b33c8fb6a9.jpg?x-oss-process=image/resize,w_260,h_260","name":"汉密尔顿Hamilton","pinpai":"美国经典系列 勇者"
}]

